file_checksum/__init__.py
file_checksum/__main__.py
file_checksum/py.typed
file_checksum-1.0.0.dist-info/LICENSE
file_checksum-1.0.0.dist-info/METADATA
file_checksum-1.0.0.dist-info/WHEEL
file_checksum-1.0.0.dist-info/entry_points.txt
file_checksum-1.0.0.dist-info/RECORD
