Metadata-Version: 2.1
Name: file-checksum
Version: 1.0.0
Summary: Generate and validate checksums for files
Home-page: https://github.com/pbs-data-solutions/file-checksum
License: MIT
Keywords: python,checksum,hash
Author: Paul Sanders
Author-email: paul@pbsdatasolutions.com
Requires-Python: >=3.8,<4.0
Classifier: Development Status :: 5 - Production/Stable
Classifier: Intended Audience :: Developers
Classifier: Intended Audience :: Science/Research
Classifier: License :: OSI Approved :: MIT License
Classifier: Operating System :: OS Independent
Classifier: Programming Language :: Python :: 3
Classifier: Programming Language :: Python :: 3.8
Classifier: Programming Language :: Python :: 3.9
Classifier: Programming Language :: Python :: 3.10
Classifier: Programming Language :: Python :: 3.11
Classifier: Programming Language :: Python :: 3.10
Classifier: Programming Language :: Python :: 3.11
Classifier: Programming Language :: Python :: 3.8
Classifier: Programming Language :: Python :: 3.9
Classifier: Typing :: Typed
Requires-Dist: rich (==13.3.4)
Requires-Dist: typer (==0.7.0)
Project-URL: Documentation, https://github.com/pbs-data-solutions/file-checksum
Project-URL: Repository, https://github.com/pbs-data-solutions/file-checksum
